{
	"info": {
		"_postman_id": "3f5dc537-a23b-42b5-90dd-ed98494f01d8",
		"name": "Task app",
		"schema": "https://schema.getpostman.com/json/collection/v2.1.0/collection.json"
	},
	"item": [
		{
			"name": "Create user",
			"request": {
				"method": "POST",
				"header": [],
				"body": {
					"mode": "raw",
					"raw": "{\n\t\"name\": \"Sun Pochin\",\n\t\"email\": \"sunpochin@gmail.com\",\n\t\"password\": \"Red123!!!\"\n}\n",
					"options": {
						"raw": {
							"language": "json"
						}
					}
				},
				"url": {
					"raw": "{{url}}/users",
					"host": [
						"{{url}}"
					],
					"path": [
						"users"
					]
				},
				"description": "Create user"
			},
			"response": []
		},
		{
			"name": "Login user",
			"event": [
				{
					"listen": "test",
					"script": {
						"id": "e5cca12a-4807-4c3d-8851-d9f6fc4bb7cc",
						"exec": [
							"console.log('test begins : ')",
							"",
							"if (pm.response.code === 200) {",
							"    pm.environment.set('authToken', pm.response.json().token)",
							"    console.log('pm.response.json(): ', pm.response.json().token)",
							"}",
							"",
							"",
							""
						],
						"type": "text/javascript"
					}
				}
			],
			"request": {
				"auth": {
					"type": "bearer",
					"bearer": [
						{
							"key": "token",
							"value": "{{authToken}}",
							"type": "string"
						}
					]
				},
				"method": "POST",
				"header": [],
				"body": {
					"mode": "raw",
					"raw": "{\n\t\"email\": \"sunpochin@gmail.com\",\n\t\"password\": \"Red123!!!\"\n}",
					"options": {
						"raw": {
							"language": "json"
						}
					}
				},
				"url": {
					"raw": "{{url}}/users/login",
					"host": [
						"{{url}}"
					],
					"path": [
						"users",
						"login"
					]
				},
				"description": "Login user"
			},
			"response": []
		},
		{
			"name": "Logout user",
			"request": {
				"method": "POST",
				"header": [],
				"url": {
					"raw": "{{url}}/users/logout",
					"host": [
						"{{url}}"
					],
					"path": [
						"users",
						"logout"
					]
				},
				"description": "{{url}}/users/logout"
			},
			"response": []
		},
		{
			"name": "create task",
			"request": {
				"method": "POST",
				"header": [],
				"body": {
					"mode": "raw",
					"raw": "{\n\t\"description\": \"get born\",\n\t\"completed\": true\n}\n",
					"options": {
						"raw": {
							"language": "json"
						}
					}
				},
				"url": {
					"raw": "{{url}}/tasks",
					"host": [
						"{{url}}"
					],
					"path": [
						"tasks"
					]
				},
				"description": "localhost:3000/tasks"
			},
			"response": []
		},
		{
			"name": "upload avatar",
			"protocolProfileBehavior": {
				"disabledSystemHeaders": {
					"content-length": true
				}
			},
			"request": {
				"method": "POST",
				"header": [],
				"body": {
					"mode": "formdata",
					"formdata": [
						{
							"key": "avatarfile",
							"type": "file",
							"src": "/home/pachinko/Pictures/misc/1_tele.jpg"
						}
					]
				},
				"url": {
					"raw": "{{url}}/users/me/avatar",
					"host": [
						"{{url}}"
					],
					"path": [
						"users",
						"me",
						"avatar"
					]
				}
			},
			"response": []
		},
		{
			"name": "Upload image new",
			"request": {
				"method": "POST",
				"header": [],
				"body": {
					"mode": "formdata",
					"formdata": [
						{
							"key": "avatarfile",
							"type": "file",
							"src": "/home/pachinko/Pictures/misc/1_tele.jpg"
						}
					]
				},
				"url": {
					"raw": "{{url}}/users/me/avatar",
					"host": [
						"{{url}}"
					],
					"path": [
						"users",
						"me",
						"avatar"
					]
				}
			},
			"response": []
		},
		{
			"name": "read my profile",
			"request": {
				"method": "GET",
				"header": [],
				"url": {
					"raw": "{{url}}/users/me",
					"host": [
						"{{url}}"
					],
					"path": [
						"users",
						"me"
					]
				},
				"description": "read users"
			},
			"response": []
		},
		{
			"name": "read tasks",
			"request": {
				"method": "GET",
				"header": [],
				"url": {
					"raw": "{{url}}/tasks?limit=2&skip=2",
					"host": [
						"{{url}}"
					],
					"path": [
						"tasks"
					],
					"query": [
						{
							"key": "limit",
							"value": "2"
						},
						{
							"key": "skip",
							"value": "2"
						}
					]
				},
				"description": "localhost:3000/tasks"
			},
			"response": []
		},
		{
			"name": "read task desc aesc",
			"request": {
				"method": "GET",
				"header": [],
				"url": {
					"raw": "{{url}}/tasks?sortBy=createdAt:asc",
					"host": [
						"{{url}}"
					],
					"path": [
						"tasks"
					],
					"query": [
						{
							"key": "sortBy",
							"value": "createdAt:asc"
						}
					]
				},
				"description": "{{url}}/tasks?limit=2&skip=2"
			},
			"response": []
		},
		{
			"name": "update user",
			"request": {
				"method": "PATCH",
				"header": [],
				"body": {
					"mode": "raw",
					"raw": "{\n\t\"age\": 22,\n\t\"name\": \"sss\"\n}",
					"options": {
						"raw": {
							"language": "json"
						}
					}
				},
				"url": {
					"raw": "{{url}}/users/me",
					"host": [
						"{{url}}"
					],
					"path": [
						"users",
						"me"
					]
				}
			},
			"response": []
		},
		{
			"name": "Delete user",
			"request": {
				"method": "DELETE",
				"header": [],
				"url": {
					"raw": "{{url}}/users/me",
					"host": [
						"{{url}}"
					],
					"path": [
						"users",
						"me"
					]
				}
			},
			"response": []
		},
		{
			"name": "update task",
			"request": {
				"method": "PATCH",
				"header": [],
				"body": {
					"mode": "raw",
					"raw": "",
					"options": {
						"raw": {
							"language": "json"
						}
					}
				},
				"url": {
					"raw": "{{url}}/tasks",
					"host": [
						"{{url}}"
					],
					"path": [
						"tasks"
					]
				},
				"description": "{{url}}/tasks"
			},
			"response": []
		}
	],
	"auth": {
		"type": "bearer",
		"bearer": [
			{
				"key": "token",
				"value": "{{authToken}}",
				"type": "string"
			}
		]
	},
	"event": [
		{
			"listen": "prerequest",
			"script": {
				"id": "ec70532e-d25a-46ec-ba00-324a91914f04",
				"type": "text/javascript",
				"exec": [
					""
				]
			}
		},
		{
			"listen": "test",
			"script": {
				"id": "56d7fd9b-0070-4c01-bff5-ecc418b626d7",
				"type": "text/javascript",
				"exec": [
					""
				]
			}
		}
	],
	"protocolProfileBehavior": {}
}